jortt_report/__init__.py
jortt_report/__main__.py
jortt_report/auth.py
jortt_report/datamart.py
jortt_report/pipeline.py
jortt_report/tui.py
jortt_report-0.1.3.dist-info/METADATA
jortt_report-0.1.3.dist-info/WHEEL
jortt_report-0.1.3.dist-info/entry_points.txt
jortt_report-0.1.3.dist-info/licenses/LICENSE
jortt_report-0.1.3.dist-info/RECORD
