Metadata-Version: 2.4
Name: jortt-report
Version: 0.1.3
Summary: Terminal-based timesheet reporting for Jortt with DuckDB backend
Project-URL: Homepage, https://github.com/dkapitan/jortt-report
Project-URL: Repository, https://github.com/dkapitan/jortt-report
Project-URL: Issues, https://github.com/dkapitan/jortt-report/issues
Author-email: Daniel Kapitan <daniel@kapitan.net>
License: GPL-3.0-or-later
License-File: LICENSE
Keywords: dlt,duckdb,jortt,reporting,timesheet,tui
Classifier: Development Status :: 4 - Beta
Classifier: Intended Audience :: Developers
Classifier: Intended Audience :: End Users/Desktop
Classifier: License :: OSI Approved :: GNU General Public License v3 or later (GPLv3+)
Classifier: Programming Language :: Python :: 3
Classifier: Programming Language :: Python :: 3.11
Classifier: Programming Language :: Python :: 3.12
Classifier: Programming Language :: Python :: 3.13
Classifier: Topic :: Office/Business
Classifier: Topic :: Terminals
Requires-Python: >=3.11
Requires-Dist: boring-semantic-layer>=0.2.0
Requires-Dist: dlt[duckdb]>=1.20.0
Requires-Dist: polars>=1.36.1
Requires-Dist: pyarrow>=22.0.0
Requires-Dist: python-dotenv>=1.2.1
Requires-Dist: requests>=2.32.5
Requires-Dist: textual>=7.2.0
Requires-Dist: tqdm>=4.67.1
Provides-Extra: dev
Requires-Dist: pytest-cov>=4.1.0; extra == 'dev'
Requires-Dist: pytest>=8.0.0; extra == 'dev'
